omero_user_token/__init__.py
omero_user_token/cli/__init__.py
omero_user_token/cli/omero_user_token.py
omero_user_token-0.4.1.dist-info/LICENSE.txt
omero_user_token-0.4.1.dist-info/METADATA
omero_user_token-0.4.1.dist-info/WHEEL
omero_user_token-0.4.1.dist-info/entry_points.txt
omero_user_token-0.4.1.dist-info/top_level.txt
omero_user_token-0.4.1.dist-info/RECORD
