Metadata-Version: 2.2
Name: omero-user-token
Version: 0.4.1
Summary: OMERO user token management system
Author-email: "Glencoe Software, Inc." <info@glencoesoftware.com>
License: 		    GNU GENERAL PUBLIC LICENSE
Project-URL: Repository, https://github.com/glencoesoftware/omero-user-token
Classifier: Development Status :: 5 - Production/Stable
Classifier: License :: OSI Approved :: GNU General Public License v2 (GPLv2)
Classifier: Intended Audience :: Science/Research
Classifier: Intended Audience :: Developers
Classifier: Programming Language :: Python :: 3.9
Classifier: Programming Language :: Python :: 3.10
Classifier: Programming Language :: Python :: 3.11
Classifier: Programming Language :: Python :: 3.12
Requires-Python: >=3.9
License-File: LICENSE.txt
Requires-Dist: click>=7.0
Requires-Dist: configparser==4.0.2
Requires-Dist: omero-py>5.6
Provides-Extra: dev
Requires-Dist: pytest; extra == "dev"
